etronome/__init__.py
etronome/__main__.py
etronome/beat_counter.py
etronome/controller.py
etronome/model.py
etronome/observable.py
etronome/sound.py
etronome/utils.py
etronome/assets/__init__.py
etronome/assets/click.wav
etronome/view/__init__.py
etronome/view/controls.py
etronome/view/display.py
etronome/view/play_pause.py
etronome/view/tapper.py
etronome/view/top_view.py
etronome-0.1.2.dist-info/LICENSE
etronome-0.1.2.dist-info/METADATA
etronome-0.1.2.dist-info/WHEEL
etronome-0.1.2.dist-info/top_level.txt
etronome-0.1.2.dist-info/RECORD
