Metadata-Version: 2.1
Name: etronome
Version: 0.1.2
Summary: Keep track of a rythm
Home-page: https://github.com/wpbindt/metronome
Author: Wessel Bindt
Author-email: wesselbindt@gmail.com
License: GNU
Platform: UNKNOWN
Classifier: License :: OSI Approved :: GNU General Public License v3 or later (GPLv3+)
Classifier: Programming Language :: Python :: 3.8
